{
  "id": "a118e664-2d71-4433-aacf-5e55604f703f",
  "prevId": "4c1422f2-f367-471e-a4fc-431fd9ca2786",
  "version": "7",
  "dialect": "postgresql",
  "tables": {
    "public.feedback": {
      "name": "feedback",
      "schema": "",
      "columns": {
        "id": {
          "name": "id",
          "type": "serial",
          "primaryKey": true,
          "notNull": true
        },
        "student_id": {
          "name": "student_id",
          "type": "integer",
          "primaryKey": false,
          "notNull": true
        },
        "date": {
          "name": "date",
          "type": "date",
          "primaryKey": false,
          "notNull": true
        },
        "meal_type": {
          "name": "meal_type",
          "type": "varchar(20)",
          "primaryKey": false,
          "notNull": true
        },
        "rating": {
          "name": "rating",
          "type": "integer",
          "primaryKey": false,
          "notNull": true,
          "default": 5
        },
        "comment": {
          "name": "comment",
          "type": "text",
          "primaryKey": false,
          "notNull": false,
          "default": "''"
        },
        "created_at": {
          "name": "created_at",
          "type": "timestamp",
          "primaryKey": false,
          "notNull": true,
          "default": "now()"
        }
      },
      "indexes": {},
      "foreignKeys": {
        "feedback_student_id_users_id_fk": {
          "name": "feedback_student_id_users_id_fk",
          "tableFrom": "feedback",
          "tableTo": "users",
          "columnsFrom": [
            "student_id"
          ],
          "columnsTo": [
            "id"
          ],
          "onDelete": "cascade",
          "onUpdate": "no action"
        }
      },
      "compositePrimaryKeys": {},
      "uniqueConstraints": {},
      "policies": {},
      "checkConstraints": {},
      "isRLSEnabled": false
    },
    "public.food_items": {
      "name": "food_items",
      "schema": "",
      "columns": {
        "id": {
          "name": "id",
          "type": "serial",
          "primaryKey": true,
          "notNull": true
        },
        "name": {
          "name": "name",
          "type": "varchar(255)",
          "primaryKey": false,
          "notNull": true
        }
      },
      "indexes": {},
      "foreignKeys": {},
      "compositePrimaryKeys": {},
      "uniqueConstraints": {
        "food_items_name_unique": {
          "name": "food_items_name_unique",
          "nullsNotDistinct": false,
          "columns": [
            "name"
          ]
        }
      },
      "policies": {},
      "checkConstraints": {},
      "isRLSEnabled": false
    },
    "public.holidays": {
      "name": "holidays",
      "schema": "",
      "columns": {
        "id": {
          "name": "id",
          "type": "serial",
          "primaryKey": true,
          "notNull": true
        },
        "date": {
          "name": "date",
          "type": "date",
          "primaryKey": false,
          "notNull": true
        },
        "reason": {
          "name": "reason",
          "type": "varchar(255)",
          "primaryKey": false,
          "notNull": true
        },
        "created_at": {
          "name": "created_at",
          "type": "timestamp",
          "primaryKey": false,
          "notNull": true,
          "default": "now()"
        }
      },
      "indexes": {},
      "foreignKeys": {},
      "compositePrimaryKeys": {},
      "uniqueConstraints": {},
      "policies": {},
      "checkConstraints": {},
      "isRLSEnabled": false
    },
    "public.meal_distribution_history": {
      "name": "meal_distribution_history",
      "schema": "",
      "columns": {
        "id": {
          "name": "id",
          "type": "serial",
          "primaryKey": true,
          "notNull": true
        },
        "student_id": {
          "name": "student_id",
          "type": "integer",
          "primaryKey": false,
          "notNull": true
        },
        "meal_id": {
          "name": "meal_id",
          "type": "integer",
          "primaryKey": false,
          "notNull": true
        },
        "served_at": {
          "name": "served_at",
          "type": "timestamp",
          "primaryKey": false,
          "notNull": true,
          "default": "now()"
        },
        "staff_id": {
          "name": "staff_id",
          "type": "integer",
          "primaryKey": false,
          "notNull": true
        }
      },
      "indexes": {},
      "foreignKeys": {
        "meal_distribution_history_student_id_users_id_fk": {
          "name": "meal_distribution_history_student_id_users_id_fk",
          "tableFrom": "meal_distribution_history",
          "tableTo": "users",
          "columnsFrom": [
            "student_id"
          ],
          "columnsTo": [
            "id"
          ],
          "onDelete": "cascade",
          "onUpdate": "no action"
        },
        "meal_distribution_history_meal_id_meals_id_fk": {
          "name": "meal_distribution_history_meal_id_meals_id_fk",
          "tableFrom": "meal_distribution_history",
          "tableTo": "meals",
          "columnsFrom": [
            "meal_id"
          ],
          "columnsTo": [
            "id"
          ],
          "onDelete": "cascade",
          "onUpdate": "no action"
        },
        "meal_distribution_history_staff_id_users_id_fk": {
          "name": "meal_distribution_history_staff_id_users_id_fk",
          "tableFrom": "meal_distribution_history",
          "tableTo": "users",
          "columnsFrom": [
            "staff_id"
          ],
          "columnsTo": [
            "id"
          ],
          "onDelete": "no action",
          "onUpdate": "no action"
        }
      },
      "compositePrimaryKeys": {},
      "uniqueConstraints": {},
      "policies": {},
      "checkConstraints": {},
      "isRLSEnabled": false
    },
    "public.meal_food_items": {
      "name": "meal_food_items",
      "schema": "",
      "columns": {
        "id": {
          "name": "id",
          "type": "serial",
          "primaryKey": true,
          "notNull": true
        },
        "meal_id": {
          "name": "meal_id",
          "type": "integer",
          "primaryKey": false,
          "notNull": true
        },
        "food_item_id": {
          "name": "food_item_id",
          "type": "integer",
          "primaryKey": false,
          "notNull": true
        }
      },
      "indexes": {},
      "foreignKeys": {
        "meal_food_items_meal_id_meals_id_fk": {
          "name": "meal_food_items_meal_id_meals_id_fk",
          "tableFrom": "meal_food_items",
          "tableTo": "meals",
          "columnsFrom": [
            "meal_id"
          ],
          "columnsTo": [
            "id"
          ],
          "onDelete": "cascade",
          "onUpdate": "no action"
        },
        "meal_food_items_food_item_id_food_items_id_fk": {
          "name": "meal_food_items_food_item_id_food_items_id_fk",
          "tableFrom": "meal_food_items",
          "tableTo": "food_items",
          "columnsFrom": [
            "food_item_id"
          ],
          "columnsTo": [
            "id"
          ],
          "onDelete": "cascade",
          "onUpdate": "no action"
        }
      },
      "compositePrimaryKeys": {},
      "uniqueConstraints": {},
      "policies": {},
      "checkConstraints": {},
      "isRLSEnabled": false
    },
    "public.meal_selections": {
      "name": "meal_selections",
      "schema": "",
      "columns": {
        "id": {
          "name": "id",
          "type": "serial",
          "primaryKey": true,
          "notNull": true
        },
        "student_id": {
          "name": "student_id",
          "type": "integer",
          "primaryKey": false,
          "notNull": true
        },
        "date": {
          "name": "date",
          "type": "date",
          "primaryKey": false,
          "notNull": true
        },
        "breakfast": {
          "name": "breakfast",
          "type": "boolean",
          "primaryKey": false,
          "notNull": true,
          "default": false
        },
        "lunch": {
          "name": "lunch",
          "type": "boolean",
          "primaryKey": false,
          "notNull": true,
          "default": false
        },
        "dinner": {
          "name": "dinner",
          "type": "boolean",
          "primaryKey": false,
          "notNull": true,
          "default": false
        },
        "created_at": {
          "name": "created_at",
          "type": "timestamp",
          "primaryKey": false,
          "notNull": true,
          "default": "now()"
        },
        "updated_at": {
          "name": "updated_at",
          "type": "timestamp",
          "primaryKey": false,
          "notNull": true,
          "default": "now()"
        }
      },
      "indexes": {},
      "foreignKeys": {
        "meal_selections_student_id_users_id_fk": {
          "name": "meal_selections_student_id_users_id_fk",
          "tableFrom": "meal_selections",
          "tableTo": "users",
          "columnsFrom": [
            "student_id"
          ],
          "columnsTo": [
            "id"
          ],
          "onDelete": "cascade",
          "onUpdate": "no action"
        }
      },
      "compositePrimaryKeys": {},
      "uniqueConstraints": {},
      "policies": {},
      "checkConstraints": {},
      "isRLSEnabled": false
    },
    "public.meal_served": {
      "name": "meal_served",
      "schema": "",
      "columns": {
        "id": {
          "name": "id",
          "type": "serial",
          "primaryKey": true,
          "notNull": true
        },
        "student_id": {
          "name": "student_id",
          "type": "integer",
          "primaryKey": false,
          "notNull": true
        },
        "date": {
          "name": "date",
          "type": "date",
          "primaryKey": false,
          "notNull": true
        },
        "meal_type": {
          "name": "meal_type",
          "type": "varchar(20)",
          "primaryKey": false,
          "notNull": true
        },
        "served_at": {
          "name": "served_at",
          "type": "timestamp",
          "primaryKey": false,
          "notNull": true,
          "default": "now()"
        },
        "staff_id": {
          "name": "staff_id",
          "type": "integer",
          "primaryKey": false,
          "notNull": true
        }
      },
      "indexes": {},
      "foreignKeys": {
        "meal_served_student_id_users_id_fk": {
          "name": "meal_served_student_id_users_id_fk",
          "tableFrom": "meal_served",
          "tableTo": "users",
          "columnsFrom": [
            "student_id"
          ],
          "columnsTo": [
            "id"
          ],
          "onDelete": "cascade",
          "onUpdate": "no action"
        },
        "meal_served_staff_id_users_id_fk": {
          "name": "meal_served_staff_id_users_id_fk",
          "tableFrom": "meal_served",
          "tableTo": "users",
          "columnsFrom": [
            "staff_id"
          ],
          "columnsTo": [
            "id"
          ],
          "onDelete": "no action",
          "onUpdate": "no action"
        }
      },
      "compositePrimaryKeys": {},
      "uniqueConstraints": {},
      "policies": {},
      "checkConstraints": {},
      "isRLSEnabled": false
    },
    "public.meals": {
      "name": "meals",
      "schema": "",
      "columns": {
        "id": {
          "name": "id",
          "type": "serial",
          "primaryKey": true,
          "notNull": true
        },
        "date": {
          "name": "date",
          "type": "date",
          "primaryKey": false,
          "notNull": true
        },
        "meal_type": {
          "name": "meal_type",
          "type": "varchar(20)",
          "primaryKey": false,
          "notNull": true
        },
        "published": {
          "name": "published",
          "type": "boolean",
          "primaryKey": false,
          "notNull": true,
          "default": false
        },
        "created_at": {
          "name": "created_at",
          "type": "timestamp",
          "primaryKey": false,
          "notNull": true,
          "default": "now()"
        }
      },
      "indexes": {},
      "foreignKeys": {},
      "compositePrimaryKeys": {},
      "uniqueConstraints": {},
      "policies": {},
      "checkConstraints": {},
      "isRLSEnabled": false
    },
    "public.menu": {
      "name": "menu",
      "schema": "",
      "columns": {
        "id": {
          "name": "id",
          "type": "serial",
          "primaryKey": true,
          "notNull": true
        },
        "date": {
          "name": "date",
          "type": "date",
          "primaryKey": false,
          "notNull": true
        },
        "meal_type": {
          "name": "meal_type",
          "type": "varchar(20)",
          "primaryKey": false,
          "notNull": true
        },
        "food_items": {
          "name": "food_items",
          "type": "jsonb",
          "primaryKey": false,
          "notNull": true,
          "default": "'[]'::jsonb"
        },
        "published": {
          "name": "published",
          "type": "boolean",
          "primaryKey": false,
          "notNull": true,
          "default": false
        },
        "created_at": {
          "name": "created_at",
          "type": "timestamp",
          "primaryKey": false,
          "notNull": true,
          "default": "now()"
        }
      },
      "indexes": {},
      "foreignKeys": {},
      "compositePrimaryKeys": {},
      "uniqueConstraints": {},
      "policies": {},
      "checkConstraints": {},
      "isRLSEnabled": false
    },
    "public.notifications": {
      "name": "notifications",
      "schema": "",
      "columns": {
        "id": {
          "name": "id",
          "type": "serial",
          "primaryKey": true,
          "notNull": true
        },
        "title": {
          "name": "title",
          "type": "varchar(255)",
          "primaryKey": false,
          "notNull": true
        },
        "message": {
          "name": "message",
          "type": "text",
          "primaryKey": false,
          "notNull": true
        },
        "created_at": {
          "name": "created_at",
          "type": "timestamp",
          "primaryKey": false,
          "notNull": true,
          "default": "now()"
        }
      },
      "indexes": {},
      "foreignKeys": {},
      "compositePrimaryKeys": {},
      "uniqueConstraints": {},
      "policies": {},
      "checkConstraints": {},
      "isRLSEnabled": false
    },
    "public.staff": {
      "name": "staff",
      "schema": "",
      "columns": {
        "id": {
          "name": "id",
          "type": "serial",
          "primaryKey": true,
          "notNull": true
        },
        "user_id": {
          "name": "user_id",
          "type": "integer",
          "primaryKey": false,
          "notNull": true
        },
        "designation": {
          "name": "designation",
          "type": "varchar(100)",
          "primaryKey": false,
          "notNull": true,
          "default": "'Cook'"
        }
      },
      "indexes": {},
      "foreignKeys": {
        "staff_user_id_users_id_fk": {
          "name": "staff_user_id_users_id_fk",
          "tableFrom": "staff",
          "tableTo": "users",
          "columnsFrom": [
            "user_id"
          ],
          "columnsTo": [
            "id"
          ],
          "onDelete": "cascade",
          "onUpdate": "no action"
        }
      },
      "compositePrimaryKeys": {},
      "uniqueConstraints": {
        "staff_user_id_unique": {
          "name": "staff_user_id_unique",
          "nullsNotDistinct": false,
          "columns": [
            "user_id"
          ]
        }
      },
      "policies": {},
      "checkConstraints": {},
      "isRLSEnabled": false
    },
    "public.student_meal_selections": {
      "name": "student_meal_selections",
      "schema": "",
      "columns": {
        "id": {
          "name": "id",
          "type": "serial",
          "primaryKey": true,
          "notNull": true
        },
        "student_id": {
          "name": "student_id",
          "type": "integer",
          "primaryKey": false,
          "notNull": true
        },
        "meal_id": {
          "name": "meal_id",
          "type": "integer",
          "primaryKey": false,
          "notNull": true
        },
        "food_item_id": {
          "name": "food_item_id",
          "type": "integer",
          "primaryKey": false,
          "notNull": true
        },
        "created_at": {
          "name": "created_at",
          "type": "timestamp",
          "primaryKey": false,
          "notNull": true,
          "default": "now()"
        }
      },
      "indexes": {},
      "foreignKeys": {
        "student_meal_selections_student_id_users_id_fk": {
          "name": "student_meal_selections_student_id_users_id_fk",
          "tableFrom": "student_meal_selections",
          "tableTo": "users",
          "columnsFrom": [
            "student_id"
          ],
          "columnsTo": [
            "id"
          ],
          "onDelete": "cascade",
          "onUpdate": "no action"
        },
        "student_meal_selections_meal_id_meals_id_fk": {
          "name": "student_meal_selections_meal_id_meals_id_fk",
          "tableFrom": "student_meal_selections",
          "tableTo": "meals",
          "columnsFrom": [
            "meal_id"
          ],
          "columnsTo": [
            "id"
          ],
          "onDelete": "cascade",
          "onUpdate": "no action"
        },
        "student_meal_selections_food_item_id_food_items_id_fk": {
          "name": "student_meal_selections_food_item_id_food_items_id_fk",
          "tableFrom": "student_meal_selections",
          "tableTo": "food_items",
          "columnsFrom": [
            "food_item_id"
          ],
          "columnsTo": [
            "id"
          ],
          "onDelete": "cascade",
          "onUpdate": "no action"
        }
      },
      "compositePrimaryKeys": {},
      "uniqueConstraints": {},
      "policies": {},
      "checkConstraints": {},
      "isRLSEnabled": false
    },
    "public.students": {
      "name": "students",
      "schema": "",
      "columns": {
        "id": {
          "name": "id",
          "type": "serial",
          "primaryKey": true,
          "notNull": true
        },
        "user_id": {
          "name": "user_id",
          "type": "integer",
          "primaryKey": false,
          "notNull": true
        },
        "course": {
          "name": "course",
          "type": "varchar(100)",
          "primaryKey": false,
          "notNull": true,
          "default": "'B.Tech'"
        },
        "year": {
          "name": "year",
          "type": "integer",
          "primaryKey": false,
          "notNull": true,
          "default": 1
        },
        "hostel": {
          "name": "hostel",
          "type": "varchar(100)",
          "primaryKey": false,
          "notNull": true,
          "default": "'Hostel A'"
        },
        "roll_number": {
          "name": "roll_number",
          "type": "varchar(50)",
          "primaryKey": false,
          "notNull": true,
          "default": "''"
        }
      },
      "indexes": {},
      "foreignKeys": {
        "students_user_id_users_id_fk": {
          "name": "students_user_id_users_id_fk",
          "tableFrom": "students",
          "tableTo": "users",
          "columnsFrom": [
            "user_id"
          ],
          "columnsTo": [
            "id"
          ],
          "onDelete": "cascade",
          "onUpdate": "no action"
        }
      },
      "compositePrimaryKeys": {},
      "uniqueConstraints": {
        "students_user_id_unique": {
          "name": "students_user_id_unique",
          "nullsNotDistinct": false,
          "columns": [
            "user_id"
          ]
        }
      },
      "policies": {},
      "checkConstraints": {},
      "isRLSEnabled": false
    },
    "public.users": {
      "name": "users",
      "schema": "",
      "columns": {
        "id": {
          "name": "id",
          "type": "serial",
          "primaryKey": true,
          "notNull": true
        },
        "name": {
          "name": "name",
          "type": "varchar(255)",
          "primaryKey": false,
          "notNull": true
        },
        "email": {
          "name": "email",
          "type": "varchar(255)",
          "primaryKey": false,
          "notNull": true
        },
        "password": {
          "name": "password",
          "type": "varchar(255)",
          "primaryKey": false,
          "notNull": true
        },
        "role": {
          "name": "role",
          "type": "varchar(20)",
          "primaryKey": false,
          "notNull": true,
          "default": "'student'"
        },
        "created_at": {
          "name": "created_at",
          "type": "timestamp",
          "primaryKey": false,
          "notNull": true,
          "default": "now()"
        }
      },
      "indexes": {},
      "foreignKeys": {},
      "compositePrimaryKeys": {},
      "uniqueConstraints": {
        "users_email_unique": {
          "name": "users_email_unique",
          "nullsNotDistinct": false,
          "columns": [
            "email"
          ]
        }
      },
      "policies": {},
      "checkConstraints": {},
      "isRLSEnabled": false
    }
  },
  "enums": {},
  "schemas": {},
  "sequences": {},
  "roles": {},
  "policies": {},
  "views": {},
  "_meta": {
    "columns": {},
    "schemas": {},
    "tables": {}
  }
}